{"44001030100":{"scores":{"income":81,"rent":61,"homeValue":64,"studentPopulation":72},"raw":{"income":137237,"rent":1750,"homeValue":581500,"studentPopulation":1523,"population":5085,"name":"Census Tract 301; Bristol County; Rhode Island"}},"44001030200":{"scores":{"income":77,"rent":68,"homeValue":63,"studentPopulation":50},"raw":{"income":130455,"rent":1938,"homeValue":562800,"studentPopulation":952,"population":3210,"name":"Census Tract 302; Bristol County; Rhode Island"}},"44001030300":{"scores":{"income":100,"rent":null,"homeValue":68,"studentPopulation":62},"raw":{"income":172672,"rent":null,"homeValue":630700,"studentPopulation":1268,"population":4671,"name":"Census Tract 303; Bristol County; Rhode Island"}},"44001030400":{"scores":{"income":100,"rent":100,"homeValue":97,"studentPopulation":69},"raw":{"income":224500,"rent":3501,"homeValue":989300,"studentPopulation":1430,"population":4160,"name":"Census Tract 304; Bristol County; Rhode Island"}},"44001030500":{"scores":{"income":46,"rent":48,"homeValue":48,"studentPopulation":36},"raw":{"income":79552,"rent":1423,"homeValue":372200,"studentPopulation":578,"population":3572,"name":"Census Tract 305; Bristol County; Rhode Island"}},"44001030601":{"scores":{"income":74,"rent":54,"homeValue":50,"studentPopulation":35},"raw":{"income":125781,"rent":1571,"homeValue":399000,"studentPopulation":571,"population":3472,"name":"Census Tract 306.01; Bristol County; Rhode Island"}},"44001030602":{"scores":{"income":44,"rent":38,"homeValue":51,"studentPopulation":32},"raw":{"income":77281,"rent":1165,"homeValue":411800,"studentPopulation":483,"population":4100,"name":"Census Tract 306.02; Bristol County; Rhode Island"}},"44001030700":{"scores":{"income":41,"rent":56,"homeValue":56,"studentPopulation":46},"raw":{"income":70850,"rent":1633,"homeValue":470200,"studentPopulation":855,"population":3389,"name":"Census Tract 307; Bristol County; Rhode Island"}},"44001030800":{"scores":{"income":58,"rent":56,"homeValue":56,"studentPopulation":100},"raw":{"income":100260,"rent":1636,"homeValue":476200,"studentPopulation":3042,"population":6074,"name":"Census Tract 308; Bristol County; Rhode Island"}},"44001030901":{"scores":{"income":68,"rent":55,"homeValue":55,"studentPopulation":67},"raw":{"income":116688,"rent":1606,"homeValue":459000,"studentPopulation":1379,"population":6210,"name":"Census Tract 309.01; Bristol County; Rhode Island"}},"44001030902":{"scores":{"income":58,"rent":39,"homeValue":62,"studentPopulation":69},"raw":{"income":98722,"rent":1198,"homeValue":555300,"studentPopulation":1450,"population":6547,"name":"Census Tract 309.02; Bristol County; Rhode Island"}},"44003020101":{"scores":{"income":57,"rent":40,"homeValue":45,"studentPopulation":67},"raw":{"income":98387,"rent":1207,"homeValue":335200,"studentPopulation":1387,"population":7113,"name":"Census Tract 201.01; Kent County; Rhode Island"}},"44003020102":{"scores":{"income":38,"rent":50,"homeValue":47,"studentPopulation":37},"raw":{"income":65903,"rent":1483,"homeValue":356800,"studentPopulation":619,"population":4877,"name":"Census Tract 201.02; Kent County; Rhode Island"}},"44003020200":{"scores":{"income":36,"rent":41,"homeValue":43,"studentPopulation":62},"raw":{"income":64063,"rent":1239,"homeValue":306000,"studentPopulation":1248,"population":5475,"name":"Census Tract 202; Kent County; Rhode Island"}},"44003020300":{"scores":{"income":40,"rent":39,"homeValue":44,"studentPopulation":43},"raw":{"income":70120,"rent":1182,"homeValue":320200,"studentPopulation":766,"population":5815,"name":"Census Tract 203; Kent County; Rhode Island"}},"44003020400":{"scores":{"income":45,"rent":55,"homeValue":45,"studentPopulation":37},"raw":{"income":78133,"rent":1596,"homeValue":329100,"studentPopulation":618,"population":3235,"name":"Census Tract 204; Kent County; Rhode Island"}},"44003020500":{"scores":{"income":61,"rent":45,"homeValue":45,"studentPopulation":52},"raw":{"income":105048,"rent":1354,"homeValue":332900,"studentPopulation":1003,"population":4658,"name":"Census Tract 205; Kent County; Rhode Island"}},"44003020601":{"scores":{"income":77,"rent":40,"homeValue":47,"studentPopulation":66},"raw":{"income":130699,"rent":1227,"homeValue":360900,"studentPopulation":1372,"population":6768,"name":"Census Tract 206.01; Kent County; Rhode Island"}},"44003020602":{"scores":{"income":44,"rent":44,"homeValue":37,"studentPopulation":35},"raw":{"income":76083,"rent":1326,"homeValue":234600,"studentPopulation":558,"population":3412,"name":"Census Tract 206.02; Kent County; Rhode Island"}},"44003020603":{"scores":{"income":56,"rent":35,"homeValue":44,"studentPopulation":50},"raw":{"income":95795,"rent":1099,"homeValue":324600,"studentPopulation":953,"population":6462,"name":"Census Tract 206.03; Kent County; Rhode Island"}},"44003020604":{"scores":{"income":45,"rent":null,"homeValue":44,"studentPopulation":52},"raw":{"income":77912,"rent":null,"homeValue":327500,"studentPopulation":998,"population":5541,"name":"Census Tract 206.04; Kent County; Rhode Island"}},"44003020701":{"scores":{"income":77,"rent":null,"homeValue":49,"studentPopulation":32},"raw":{"income":131607,"rent":null,"homeValue":392000,"studentPopulation":482,"population":1910,"name":"Census Tract 207.01; Kent County; Rhode Island"}},"44003020702":{"scores":{"income":75,"rent":null,"homeValue":52,"studentPopulation":53},"raw":{"income":126786,"rent":null,"homeValue":430000,"studentPopulation":1032,"population":5226,"name":"Census Tract 207.02; Kent County; Rhode Island"}},"44003020703":{"scores":{"income":71,"rent":47,"homeValue":56,"studentPopulation":72},"raw":{"income":120930,"rent":1391,"homeValue":474400,"studentPopulation":1525,"population":6588,"name":"Census Tract 207.03; Kent County; Rhode Island"}},"44003020800":{"scores":{"income":80,"rent":86,"homeValue":61,"studentPopulation":70},"raw":{"income":135625,"rent":2414,"homeValue":535400,"studentPopulation":1474,"population":6647,"name":"Census Tract 208; Kent County; Rhode Island"}},"44003020901":{"scores":{"income":58,"rent":39,"homeValue":62,"studentPopulation":38},"raw":{"income":99286,"rent":1202,"homeValue":544100,"studentPopulation":640,"population":3724,"name":"Census Tract 209.01; Kent County; Rhode Island"}},"44003020903":{"scores":{"income":100,"rent":null,"homeValue":76,"studentPopulation":79},"raw":{"income":250001,"rent":null,"homeValue":733500,"studentPopulation":1693,"population":6728,"name":"Census Tract 209.03; Kent County; Rhode Island"}},"44003020904":{"scores":{"income":100,"rent":null,"homeValue":73,"studentPopulation":58},"raw":{"income":173375,"rent":null,"homeValue":683900,"studentPopulation":1160,"population":4102,"name":"Census Tract 209.04; Kent County; Rhode Island"}},"44003021001":{"scores":{"income":63,"rent":55,"homeValue":42,"studentPopulation":35},"raw":{"income":107880,"rent":1611,"homeValue":293500,"studentPopulation":570,"population":2490,"name":"Census Tract 210.01; Kent County; Rhode Island"}},"44003021002":{"scores":{"income":57,"rent":44,"homeValue":48,"studentPopulation":42},"raw":{"income":97287,"rent":1318,"homeValue":375700,"studentPopulation":741,"population":4423,"name":"Census Tract 210.02; Kent County; Rhode Island"}},"44003021100":{"scores":{"income":51,"rent":46,"homeValue":43,"studentPopulation":63},"raw":{"income":87263,"rent":1363,"homeValue":309600,"studentPopulation":1294,"population":5329,"name":"Census Tract 211; Kent County; Rhode Island"}},"44003021200":{"scores":{"income":44,"rent":41,"homeValue":45,"studentPopulation":33},"raw":{"income":77250,"rent":1234,"homeValue":340100,"studentPopulation":498,"population":3468,"name":"Census Tract 212; Kent County; Rhode Island"}},"44003021300":{"scores":{"income":54,"rent":39,"homeValue":48,"studentPopulation":53},"raw":{"income":92870,"rent":1193,"homeValue":376800,"studentPopulation":1021,"population":4596,"name":"Census Tract 213; Kent County; Rhode Island"}},"44003021401":{"scores":{"income":60,"rent":56,"homeValue":46,"studentPopulation":44},"raw":{"income":102138,"rent":1642,"homeValue":341500,"studentPopulation":788,"population":4135,"name":"Census Tract 214.01; Kent County; Rhode Island"}},"44003021402":{"scores":{"income":37,"rent":40,"homeValue":43,"studentPopulation":41},"raw":{"income":64177,"rent":1222,"homeValue":310300,"studentPopulation":706,"population":3504,"name":"Census Tract 214.02; Kent County; Rhode Island"}},"44003021501":{"scores":{"income":56,"rent":41,"homeValue":46,"studentPopulation":46},"raw":{"income":96964,"rent":1250,"homeValue":353600,"studentPopulation":845,"population":3611,"name":"Census Tract 215.01; Kent County; Rhode Island"}},"44003021502":{"scores":{"income":55,"rent":51,"homeValue":46,"studentPopulation":46},"raw":{"income":94191,"rent":1493,"homeValue":343000,"studentPopulation":837,"population":4119,"name":"Census Tract 215.02; Kent County; Rhode Island"}},"44003021600":{"scores":{"income":77,"rent":null,"homeValue":57,"studentPopulation":22},"raw":{"income":130924,"rent":null,"homeValue":488400,"studentPopulation":234,"population":1544,"name":"Census Tract 216; Kent County; Rhode Island"}},"44003021700":{"scores":{"income":44,"rent":52,"homeValue":42,"studentPopulation":44},"raw":{"income":76392,"rent":1531,"homeValue":302700,"studentPopulation":801,"population":5050,"name":"Census Tract 217; Kent County; Rhode Island"}},"44003021800":{"scores":{"income":43,"rent":40,"homeValue":46,"studentPopulation":41},"raw":{"income":74757,"rent":1230,"homeValue":342100,"studentPopulation":710,"population":3864,"name":"Census Tract 218; Kent County; Rhode Island"}},"44003021901":{"scores":{"income":48,"rent":56,"homeValue":44,"studentPopulation":42},"raw":{"income":83558,"rent":1640,"homeValue":325000,"studentPopulation":747,"population":3218,"name":"Census Tract 219.01; Kent County; Rhode Island"}},"44003021902":{"scores":{"income":59,"rent":59,"homeValue":44,"studentPopulation":27},"raw":{"income":100588,"rent":1701,"homeValue":322300,"studentPopulation":356,"population":2810,"name":"Census Tract 219.02; Kent County; Rhode Island"}},"44003021903":{"scores":{"income":61,"rent":null,"homeValue":46,"studentPopulation":43},"raw":{"income":105046,"rent":null,"homeValue":348600,"studentPopulation":778,"population":3635,"name":"Census Tract 219.03; Kent County; Rhode Island"}},"44003022000":{"scores":{"income":48,"rent":35,"homeValue":46,"studentPopulation":45},"raw":{"income":83616,"rent":1078,"homeValue":347700,"studentPopulation":818,"population":3582,"name":"Census Tract 220; Kent County; Rhode Island"}},"44003022100":{"scores":{"income":59,"rent":56,"homeValue":47,"studentPopulation":75},"raw":{"income":100935,"rent":1621,"homeValue":360300,"studentPopulation":1603,"population":6412,"name":"Census Tract 221; Kent County; Rhode Island"}},"44003022201":{"scores":{"income":88,"rent":55,"homeValue":59,"studentPopulation":72},"raw":{"income":149020,"rent":1609,"homeValue":512400,"studentPopulation":1524,"population":6837,"name":"Census Tract 222.01; Kent County; Rhode Island"}},"44003022202":{"scores":{"income":32,"rent":45,"homeValue":48,"studentPopulation":30},"raw":{"income":56500,"rent":1347,"homeValue":375700,"studentPopulation":444,"population":3860,"name":"Census Tract 222.02; Kent County; Rhode Island"}},"44003022300":{"scores":{"income":33,"rent":46,"homeValue":46,"studentPopulation":50},"raw":{"income":58880,"rent":1370,"homeValue":347500,"studentPopulation":939,"population":4473,"name":"Census Tract 223; Kent County; Rhode Island"}},"44003022400":{"scores":{"income":51,"rent":41,"homeValue":52,"studentPopulation":22},"raw":{"income":87679,"rent":1239,"homeValue":418700,"studentPopulation":229,"population":2215,"name":"Census Tract 224; Kent County; Rhode Island"}},"44003980000":{"scores":{"income":null,"rent":null,"homeValue":null,"studentPopulation":13},"raw":{"income":null,"rent":null,"homeValue":null,"studentPopulation":0,"population":null,"name":"Census Tract 9800; Kent County; Rhode Island"}},"44005040101":{"scores":{"income":55,"rent":59,"homeValue":56,"studentPopulation":60},"raw":{"income":94750,"rent":1713,"homeValue":472000,"studentPopulation":1196,"population":4812,"name":"Census Tract 401.01; Newport County; Rhode Island"}},"44005040102":{"scores":{"income":88,"rent":72,"homeValue":79,"studentPopulation":52},"raw":{"income":149770,"rent":2047,"homeValue":767300,"studentPopulation":1010,"population":5676,"name":"Census Tract 401.02; Newport County; Rhode Island"}},"44005040104":{"scores":{"income":66,"rent":59,"homeValue":65,"studentPopulation":69},"raw":{"income":113289,"rent":1702,"homeValue":585200,"studentPopulation":1434,"population":5593,"name":"Census Tract 401.04; Newport County; Rhode Island"}},"44005040105":{"scores":{"income":59,"rent":51,"homeValue":72,"studentPopulation":24},"raw":{"income":101071,"rent":1504,"homeValue":675200,"studentPopulation":271,"population":1563,"name":"Census Tract 401.05; Newport County; Rhode Island"}},"44005040200":{"scores":{"income":62,"rent":83,"homeValue":null,"studentPopulation":34},"raw":{"income":106818,"rent":2323,"homeValue":null,"studentPopulation":538,"population":1646,"name":"Census Tract 402; Newport County; Rhode Island"}},"44005040302":{"scores":{"income":44,"rent":73,"homeValue":52,"studentPopulation":31},"raw":{"income":76845,"rent":2060,"homeValue":417500,"studentPopulation":445,"population":2537,"name":"Census Tract 403.02; Newport County; Rhode Island"}},"44005040303":{"scores":{"income":44,"rent":56,"homeValue":55,"studentPopulation":47},"raw":{"income":76793,"rent":1624,"homeValue":464900,"studentPopulation":867,"population":2999,"name":"Census Tract 403.03; Newport County; Rhode Island"}},"44005040304":{"scores":{"income":50,"rent":56,"homeValue":67,"studentPopulation":34},"raw":{"income":86760,"rent":1630,"homeValue":618400,"studentPopulation":533,"population":3167,"name":"Census Tract 403.04; Newport County; Rhode Island"}},"44005040400":{"scores":{"income":78,"rent":78,"homeValue":74,"studentPopulation":63},"raw":{"income":131853,"rent":2193,"homeValue":696600,"studentPopulation":1291,"population":6483,"name":"Census Tract 404; Newport County; Rhode Island"}},"44005040500":{"scores":{"income":28,"rent":33,"homeValue":62,"studentPopulation":62},"raw":{"income":50392,"rent":1027,"homeValue":551100,"studentPopulation":1254,"population":4480,"name":"Census Tract 405; Newport County; Rhode Island"}},"44005040600":{"scores":{"income":54,"rent":60,"homeValue":68,"studentPopulation":40},"raw":{"income":93458,"rent":1724,"homeValue":629800,"studentPopulation":680,"population":4376,"name":"Census Tract 406; Newport County; Rhode Island"}},"44005040700":{"scores":{"income":69,"rent":80,"homeValue":84,"studentPopulation":30},"raw":{"income":116875,"rent":2256,"homeValue":824800,"studentPopulation":422,"population":3453,"name":"Census Tract 407; Newport County; Rhode Island"}},"44005040800":{"scores":{"income":54,"rent":56,"homeValue":94,"studentPopulation":35},"raw":{"income":93523,"rent":1632,"homeValue":956800,"studentPopulation":565,"population":2468,"name":"Census Tract 408; Newport County; Rhode Island"}},"44005040900":{"scores":{"income":57,"rent":78,"homeValue":92,"studentPopulation":79},"raw":{"income":98361,"rent":2191,"homeValue":931400,"studentPopulation":1705,"population":4706,"name":"Census Tract 409; Newport County; Rhode Island"}},"44005041000":{"scores":{"income":41,"rent":55,"homeValue":71,"studentPopulation":24},"raw":{"income":72062,"rent":1619,"homeValue":665000,"studentPopulation":289,"population":1897,"name":"Census Tract 410; Newport County; Rhode Island"}},"44005041100":{"scores":{"income":44,"rent":67,"homeValue":93,"studentPopulation":26},"raw":{"income":76964,"rent":1914,"homeValue":939500,"studentPopulation":316,"population":1429,"name":"Census Tract 411; Newport County; Rhode Island"}},"44005041200":{"scores":{"income":47,"rent":63,"homeValue":null,"studentPopulation":38},"raw":{"income":80987,"rent":1804,"homeValue":null,"studentPopulation":635,"population":2065,"name":"Census Tract 412; Newport County; Rhode Island"}},"44005041300":{"scores":{"income":83,"rent":56,"homeValue":85,"studentPopulation":45},"raw":{"income":140625,"rent":1629,"homeValue":842400,"studentPopulation":828,"population":5534,"name":"Census Tract 413; Newport County; Rhode Island"}},"44005041400":{"scores":{"income":79,"rent":null,"homeValue":80,"studentPopulation":35},"raw":{"income":134750,"rent":null,"homeValue":783400,"studentPopulation":567,"population":3584,"name":"Census Tract 414; Newport County; Rhode Island"}},"44005041601":{"scores":{"income":57,"rent":46,"homeValue":47,"studentPopulation":35},"raw":{"income":97969,"rent":1364,"homeValue":364100,"studentPopulation":566,"population":3234,"name":"Census Tract 416.01; Newport County; Rhode Island"}},"44005041602":{"scores":{"income":59,"rent":44,"homeValue":54,"studentPopulation":39},"raw":{"income":101974,"rent":1318,"homeValue":444200,"studentPopulation":662,"population":4857,"name":"Census Tract 416.02; Newport County; Rhode Island"}},"44005041701":{"scores":{"income":64,"rent":22,"homeValue":44,"studentPopulation":29},"raw":{"income":109097,"rent":759,"homeValue":327300,"studentPopulation":415,"population":3270,"name":"Census Tract 417.01; Newport County; Rhode Island"}},"44005041702":{"scores":{"income":69,"rent":48,"homeValue":56,"studentPopulation":44},"raw":{"income":117280,"rent":1429,"homeValue":479300,"studentPopulation":800,"population":4828,"name":"Census Tract 417.02; Newport County; Rhode Island"}},"44005990000":{"scores":{"income":null,"rent":null,"homeValue":null,"studentPopulation":13},"raw":{"income":null,"rent":null,"homeValue":null,"studentPopulation":0,"population":null,"name":"Census Tract 9900; Newport County; Rhode Island"}},"44007000101":{"scores":{"income":28,"rent":41,"homeValue":47,"studentPopulation":78},"raw":{"income":50208,"rent":1232,"homeValue":357000,"studentPopulation":1667,"population":3948,"name":"Census Tract 1.01; Providence County; Rhode Island"}},"44007000102":{"scores":{"income":41,"rent":56,"homeValue":43,"studentPopulation":79},"raw":{"income":71853,"rent":1626,"homeValue":309400,"studentPopulation":1702,"population":5981,"name":"Census Tract 1.02; Providence County; Rhode Island"}},"44007000200":{"scores":{"income":27,"rent":37,"homeValue":46,"studentPopulation":75},"raw":{"income":48456,"rent":1141,"homeValue":345800,"studentPopulation":1601,"population":6545,"name":"Census Tract 2; Providence County; Rhode Island"}},"44007000301":{"scores":{"income":17,"rent":33,"homeValue":51,"studentPopulation":41},"raw":{"income":32081,"rent":1026,"homeValue":410000,"studentPopulation":704,"population":2396,"name":"Census Tract 3.01; Providence County; Rhode Island"}},"44007000302":{"scores":{"income":23,"rent":27,"homeValue":47,"studentPopulation":85},"raw":{"income":42609,"rent":889,"homeValue":358900,"studentPopulation":1847,"population":5418,"name":"Census Tract 3.02; Providence County; Rhode Island"}},"44007000400":{"scores":{"income":40,"rent":38,"homeValue":50,"studentPopulation":54},"raw":{"income":70293,"rent":1172,"homeValue":398100,"studentPopulation":1063,"population":4792,"name":"Census Tract 4; Providence County; Rhode Island"}},"44007000500":{"scores":{"income":19,"rent":27,"homeValue":46,"studentPopulation":53},"raw":{"income":35616,"rent":894,"homeValue":353800,"studentPopulation":1034,"population":3459,"name":"Census Tract 5; Providence County; Rhode Island"}},"44007000600":{"scores":{"income":23,"rent":44,"homeValue":38,"studentPopulation":36},"raw":{"income":42093,"rent":1317,"homeValue":247900,"studentPopulation":597,"population":2003,"name":"Census Tract 6; Providence County; Rhode Island"}},"44007000700":{"scores":{"income":9,"rent":33,"homeValue":50,"studentPopulation":27},"raw":{"income":18164,"rent":1039,"homeValue":392900,"studentPopulation":360,"population":2399,"name":"Census Tract 7; Providence County; Rhode Island"}},"44007000800":{"scores":{"income":32,"rent":73,"homeValue":62,"studentPopulation":87},"raw":{"income":57310,"rent":2077,"homeValue":549700,"studentPopulation":1918,"population":4872,"name":"Census Tract 8; Providence County; Rhode Island"}},"44007000900":{"scores":{"income":38,"rent":51,"homeValue":56,"studentPopulation":26},"raw":{"income":67278,"rent":1493,"homeValue":473500,"studentPopulation":328,"population":2334,"name":"Census Tract 9; Providence County; Rhode Island"}},"44007001000":{"scores":{"income":33,"rent":41,"homeValue":46,"studentPopulation":27},"raw":{"income":58631,"rent":1237,"homeValue":351900,"studentPopulation":350,"population":2808,"name":"Census Tract 10; Providence County; Rhode Island"}},"44007001100":{"scores":{"income":59,"rent":61,"homeValue":47,"studentPopulation":28},"raw":{"income":100714,"rent":1756,"homeValue":357500,"studentPopulation":392,"population":2730,"name":"Census Tract 11; Providence County; Rhode Island"}},"44007001200":{"scores":{"income":31,"rent":39,"homeValue":54,"studentPopulation":47},"raw":{"income":55734,"rent":1183,"homeValue":448300,"studentPopulation":876,"population":3601,"name":"Census Tract 12; Providence County; Rhode Island"}},"44007001300":{"scores":{"income":45,"rent":52,"homeValue":54,"studentPopulation":39},"raw":{"income":78333,"rent":1522,"homeValue":450600,"studentPopulation":661,"population":3769,"name":"Census Tract 13; Providence County; Rhode Island"}},"44007001400":{"scores":{"income":34,"rent":37,"homeValue":50,"studentPopulation":79},"raw":{"income":60282,"rent":1145,"homeValue":394400,"studentPopulation":1696,"population":5996,"name":"Census Tract 14; Providence County; Rhode Island"}},"44007001500":{"scores":{"income":48,"rent":38,"homeValue":42,"studentPopulation":54},"raw":{"income":83125,"rent":1177,"homeValue":297900,"studentPopulation":1056,"population":3354,"name":"Census Tract 15; Providence County; Rhode Island"}},"44007001601":{"scores":{"income":26,"rent":44,"homeValue":38,"studentPopulation":65},"raw":{"income":46711,"rent":1313,"homeValue":244200,"studentPopulation":1343,"population":3483,"name":"Census Tract 16.01; Providence County; Rhode Island"}},"44007001602":{"scores":{"income":43,"rent":54,"homeValue":42,"studentPopulation":63},"raw":{"income":74575,"rent":1576,"homeValue":292600,"studentPopulation":1286,"population":4590,"name":"Census Tract 16.02; Providence County; Rhode Island"}},"44007001700":{"scores":{"income":30,"rent":53,"homeValue":38,"studentPopulation":54},"raw":{"income":53244,"rent":1553,"homeValue":242900,"studentPopulation":1065,"population":4084,"name":"Census Tract 17; Providence County; Rhode Island"}},"44007001800":{"scores":{"income":31,"rent":null,"homeValue":43,"studentPopulation":100},"raw":{"income":55460,"rent":null,"homeValue":313000,"studentPopulation":2480,"population":7324,"name":"Census Tract 18; Providence County; Rhode Island"}},"44007001900":{"scores":{"income":29,"rent":34,"homeValue":44,"studentPopulation":96},"raw":{"income":51348,"rent":1058,"homeValue":327400,"studentPopulation":2146,"population":6409,"name":"Census Tract 19; Providence County; Rhode Island"}},"44007002000":{"scores":{"income":58,"rent":53,"homeValue":43,"studentPopulation":100},"raw":{"income":99857,"rent":1565,"homeValue":308600,"studentPopulation":3289,"population":7867,"name":"Census Tract 20; Providence County; Rhode Island"}},"44007002101":{"scores":{"income":46,"rent":44,"homeValue":42,"studentPopulation":37},"raw":{"income":79567,"rent":1311,"homeValue":294600,"studentPopulation":608,"population":2937,"name":"Census Tract 21.01; Providence County; Rhode Island"}},"44007002102":{"scores":{"income":44,"rent":45,"homeValue":45,"studentPopulation":78},"raw":{"income":77207,"rent":1335,"homeValue":338400,"studentPopulation":1679,"population":7127,"name":"Census Tract 21.02; Providence County; Rhode Island"}},"44007002200":{"scores":{"income":39,"rent":47,"homeValue":45,"studentPopulation":80},"raw":{"income":68867,"rent":1412,"homeValue":333600,"studentPopulation":1729,"population":6436,"name":"Census Tract 22; Providence County; Rhode Island"}},"44007002300":{"scores":{"income":54,"rent":60,"homeValue":45,"studentPopulation":60},"raw":{"income":93442,"rent":1740,"homeValue":331000,"studentPopulation":1202,"population":5580,"name":"Census Tract 23; Providence County; Rhode Island"}},"44007002400":{"scores":{"income":55,"rent":49,"homeValue":48,"studentPopulation":100},"raw":{"income":94151,"rent":1463,"homeValue":368300,"studentPopulation":4112,"population":8647,"name":"Census Tract 24; Providence County; Rhode Island"}},"44007002500":{"scores":{"income":56,"rent":75,"homeValue":45,"studentPopulation":49},"raw":{"income":95896,"rent":2117,"homeValue":338500,"studentPopulation":927,"population":3484,"name":"Census Tract 25; Providence County; Rhode Island"}},"44007002600":{"scores":{"income":25,"rent":33,"homeValue":null,"studentPopulation":33},"raw":{"income":44857,"rent":1036,"homeValue":null,"studentPopulation":504,"population":2945,"name":"Census Tract 26; Providence County; Rhode Island"}},"44007002700":{"scores":{"income":22,"rent":35,"homeValue":43,"studentPopulation":69},"raw":{"income":39723,"rent":1085,"homeValue":310500,"studentPopulation":1434,"population":5127,"name":"Census Tract 27; Providence County; Rhode Island"}},"44007002801":{"scores":{"income":27,"rent":53,"homeValue":38,"studentPopulation":62},"raw":{"income":48872,"rent":1557,"homeValue":241500,"studentPopulation":1266,"population":3413,"name":"Census Tract 28.01; Providence County; Rhode Island"}},"44007002802":{"scores":{"income":20,"rent":51,"homeValue":38,"studentPopulation":37},"raw":{"income":36991,"rent":1511,"homeValue":251900,"studentPopulation":622,"population":3053,"name":"Census Tract 28.02; Providence County; Rhode Island"}},"44007002900":{"scores":{"income":24,"rent":30,"homeValue":42,"studentPopulation":64},"raw":{"income":43803,"rent":947,"homeValue":295400,"studentPopulation":1321,"population":7154,"name":"Census Tract 29; Providence County; Rhode Island"}},"44007003100":{"scores":{"income":47,"rent":57,"homeValue":60,"studentPopulation":49},"raw":{"income":80996,"rent":1653,"homeValue":526100,"studentPopulation":922,"population":4632,"name":"Census Tract 31; Providence County; Rhode Island"}},"44007003200":{"scores":{"income":63,"rent":67,"homeValue":59,"studentPopulation":54},"raw":{"income":108487,"rent":1920,"homeValue":508000,"studentPopulation":1041,"population":3506,"name":"Census Tract 32; Providence County; Rhode Island"}},"44007003300":{"scores":{"income":77,"rent":60,"homeValue":56,"studentPopulation":41},"raw":{"income":130013,"rent":1732,"homeValue":472900,"studentPopulation":718,"population":4325,"name":"Census Tract 33; Providence County; Rhode Island"}},"44007003400":{"scores":{"income":100,"rent":67,"homeValue":85,"studentPopulation":50},"raw":{"income":170000,"rent":1928,"homeValue":846100,"studentPopulation":937,"population":4823,"name":"Census Tract 34; Providence County; Rhode Island"}},"44007003500":{"scores":{"income":53,"rent":59,"homeValue":71,"studentPopulation":62},"raw":{"income":90947,"rent":1721,"homeValue":659500,"studentPopulation":1257,"population":5329,"name":"Census Tract 35; Providence County; Rhode Island"}},"44007003601":{"scores":{"income":23,"rent":61,"homeValue":100,"studentPopulation":98},"raw":{"income":42708,"rent":1766,"homeValue":1057400,"studentPopulation":2181,"population":3145,"name":"Census Tract 36.01; Providence County; Rhode Island"}},"44007003602":{"scores":{"income":86,"rent":85,"homeValue":88,"studentPopulation":100},"raw":{"income":146000,"rent":2389,"homeValue":874200,"studentPopulation":4887,"population":6018,"name":"Census Tract 36.02; Providence County; Rhode Island"}},"44007003700":{"scores":{"income":49,"rent":66,"homeValue":55,"studentPopulation":65},"raw":{"income":84766,"rent":1881,"homeValue":464700,"studentPopulation":1324,"population":3924,"name":"Census Tract 37; Providence County; Rhode Island"}},"44007010101":{"scores":{"income":57,"rent":42,"homeValue":49,"studentPopulation":42},"raw":{"income":97870,"rent":1266,"homeValue":385100,"studentPopulation":748,"population":4053,"name":"Census Tract 101.01; Providence County; Rhode Island"}},"44007010102":{"scores":{"income":53,"rent":40,"homeValue":53,"studentPopulation":34},"raw":{"income":91118,"rent":1218,"homeValue":437000,"studentPopulation":542,"population":3463,"name":"Census Tract 101.02; Providence County; Rhode Island"}},"44007010200":{"scores":{"income":29,"rent":38,"homeValue":45,"studentPopulation":50},"raw":{"income":51538,"rent":1175,"homeValue":333900,"studentPopulation":941,"population":5850,"name":"Census Tract 102; Providence County; Rhode Island"}},"44007010300":{"scores":{"income":36,"rent":null,"homeValue":44,"studentPopulation":31},"raw":{"income":63804,"rent":null,"homeValue":327600,"studentPopulation":467,"population":4321,"name":"Census Tract 103; Providence County; Rhode Island"}},"44007010400":{"scores":{"income":45,"rent":44,"homeValue":46,"studentPopulation":49},"raw":{"income":77383,"rent":1310,"homeValue":351800,"studentPopulation":921,"population":6666,"name":"Census Tract 104; Providence County; Rhode Island"}},"44007010501":{"scores":{"income":42,"rent":31,"homeValue":51,"studentPopulation":61},"raw":{"income":73851,"rent":989,"homeValue":415700,"studentPopulation":1229,"population":5121,"name":"Census Tract 105.01; Providence County; Rhode Island"}},"44007010502":{"scores":{"income":50,"rent":68,"homeValue":48,"studentPopulation":45},"raw":{"income":86546,"rent":1937,"homeValue":370200,"studentPopulation":813,"population":5098,"name":"Census Tract 105.02; Providence County; Rhode Island"}},"44007010600":{"scores":{"income":34,"rent":23,"homeValue":47,"studentPopulation":46},"raw":{"income":59375,"rent":766,"homeValue":357900,"studentPopulation":849,"population":6386,"name":"Census Tract 106; Providence County; Rhode Island"}},"44007010701":{"scores":{"income":49,"rent":52,"homeValue":48,"studentPopulation":23},"raw":{"income":85417,"rent":1541,"homeValue":371900,"studentPopulation":244,"population":2029,"name":"Census Tract 107.01; Providence County; Rhode Island"}},"44007010702":{"scores":{"income":70,"rent":38,"homeValue":46,"studentPopulation":44},"raw":{"income":119491,"rent":1160,"homeValue":345400,"studentPopulation":802,"population":4294,"name":"Census Tract 107.02; Providence County; Rhode Island"}},"44007010800":{"scores":{"income":30,"rent":32,"homeValue":50,"studentPopulation":69},"raw":{"income":52694,"rent":1005,"homeValue":394600,"studentPopulation":1445,"population":6300,"name":"Census Tract 108; Providence County; Rhode Island"}},"44007010900":{"scores":{"income":28,"rent":41,"homeValue":44,"studentPopulation":63},"raw":{"income":49777,"rent":1234,"homeValue":327400,"studentPopulation":1286,"population":5439,"name":"Census Tract 109; Providence County; Rhode Island"}},"44007011000":{"scores":{"income":30,"rent":42,"homeValue":47,"studentPopulation":89},"raw":{"income":53361,"rent":1278,"homeValue":358600,"studentPopulation":1960,"population":6274,"name":"Census Tract 110; Providence County; Rhode Island"}},"44007011100":{"scores":{"income":23,"rent":42,"homeValue":45,"studentPopulation":61},"raw":{"income":41791,"rent":1280,"homeValue":340200,"studentPopulation":1233,"population":4688,"name":"Census Tract 111; Providence County; Rhode Island"}},"44007011200":{"scores":{"income":43,"rent":46,"homeValue":46,"studentPopulation":71},"raw":{"income":74113,"rent":1371,"homeValue":347400,"studentPopulation":1503,"population":6334,"name":"Census Tract 112; Providence County; Rhode Island"}},"44007011301":{"scores":{"income":66,"rent":40,"homeValue":50,"studentPopulation":54},"raw":{"income":112313,"rent":1230,"homeValue":404000,"studentPopulation":1063,"population":4357,"name":"Census Tract 113.01; Providence County; Rhode Island"}},"44007011302":{"scores":{"income":69,"rent":54,"homeValue":52,"studentPopulation":50},"raw":{"income":118418,"rent":1576,"homeValue":423900,"studentPopulation":941,"population":4618,"name":"Census Tract 113.02; Providence County; Rhode Island"}},"44007011402":{"scores":{"income":90,"rent":75,"homeValue":61,"studentPopulation":49},"raw":{"income":151667,"rent":2112,"homeValue":541700,"studentPopulation":923,"population":4156,"name":"Census Tract 114.02; Providence County; Rhode Island"}},"44007011403":{"scores":{"income":75,"rent":39,"homeValue":49,"studentPopulation":86},"raw":{"income":127083,"rent":1184,"homeValue":389700,"studentPopulation":1870,"population":7880,"name":"Census Tract 114.03; Providence County; Rhode Island"}},"44007011404":{"scores":{"income":81,"rent":16,"homeValue":59,"studentPopulation":63},"raw":{"income":136964,"rent":601,"homeValue":509700,"studentPopulation":1291,"population":4889,"name":"Census Tract 114.04; Providence County; Rhode Island"}},"44007011405":{"scores":{"income":83,"rent":64,"homeValue":56,"studentPopulation":63},"raw":{"income":141211,"rent":1839,"homeValue":471600,"studentPopulation":1290,"population":4586,"name":"Census Tract 114.05; Providence County; Rhode Island"}},"44007011500":{"scores":{"income":68,"rent":61,"homeValue":54,"studentPopulation":70},"raw":{"income":115389,"rent":1760,"homeValue":445100,"studentPopulation":1461,"population":6747,"name":"Census Tract 115; Providence County; Rhode Island"}},"44007011600":{"scores":{"income":78,"rent":13,"homeValue":58,"studentPopulation":80},"raw":{"income":131955,"rent":516,"homeValue":498900,"studentPopulation":1730,"population":6757,"name":"Census Tract 116; Providence County; Rhode Island"}},"44007011701":{"scores":{"income":41,"rent":31,"homeValue":51,"studentPopulation":54},"raw":{"income":71607,"rent":997,"homeValue":408700,"studentPopulation":1040,"population":4738,"name":"Census Tract 117.01; Providence County; Rhode Island"}},"44007011702":{"scores":{"income":57,"rent":58,"homeValue":50,"studentPopulation":60},"raw":{"income":98594,"rent":1686,"homeValue":399800,"studentPopulation":1210,"population":4622,"name":"Census Tract 117.02; Providence County; Rhode Island"}},"44007011800":{"scores":{"income":44,"rent":44,"homeValue":44,"studentPopulation":82},"raw":{"income":77008,"rent":1312,"homeValue":323000,"studentPopulation":1778,"population":7273,"name":"Census Tract 118; Providence County; Rhode Island"}},"44007011901":{"scores":{"income":41,"rent":50,"homeValue":46,"studentPopulation":49},"raw":{"income":71492,"rent":1465,"homeValue":352100,"studentPopulation":920,"population":3464,"name":"Census Tract 119.01; Providence County; Rhode Island"}},"44007011902":{"scores":{"income":56,"rent":56,"homeValue":52,"studentPopulation":47},"raw":{"income":96227,"rent":1644,"homeValue":420000,"studentPopulation":873,"population":4913,"name":"Census Tract 119.02; Providence County; Rhode Island"}},"44007012000":{"scores":{"income":51,"rent":47,"homeValue":47,"studentPopulation":58},"raw":{"income":87961,"rent":1408,"homeValue":363500,"studentPopulation":1156,"population":6550,"name":"Census Tract 120; Providence County; Rhode Island"}},"44007012102":{"scores":{"income":46,"rent":49,"homeValue":44,"studentPopulation":36},"raw":{"income":79501,"rent":1443,"homeValue":321700,"studentPopulation":595,"population":4197,"name":"Census Tract 121.02; Providence County; Rhode Island"}},"44007012103":{"scores":{"income":39,"rent":null,"homeValue":47,"studentPopulation":34},"raw":{"income":68819,"rent":null,"homeValue":354900,"studentPopulation":530,"population":3247,"name":"Census Tract 121.03; Providence County; Rhode Island"}},"44007012104":{"scores":{"income":61,"rent":53,"homeValue":50,"studentPopulation":48},"raw":{"income":104516,"rent":1543,"homeValue":397500,"studentPopulation":897,"population":4649,"name":"Census Tract 121.04; Providence County; Rhode Island"}},"44007012200":{"scores":{"income":60,"rent":60,"homeValue":50,"studentPopulation":66},"raw":{"income":102229,"rent":1739,"homeValue":396100,"studentPopulation":1355,"population":7320,"name":"Census Tract 122; Providence County; Rhode Island"}},"44007012300":{"scores":{"income":59,"rent":56,"homeValue":45,"studentPopulation":60},"raw":{"income":100686,"rent":1620,"homeValue":336600,"studentPopulation":1210,"population":7312,"name":"Census Tract 123; Providence County; Rhode Island"}},"44007012401":{"scores":{"income":55,"rent":36,"homeValue":46,"studentPopulation":73},"raw":{"income":93838,"rent":1106,"homeValue":348300,"studentPopulation":1545,"population":7318,"name":"Census Tract 124.01; Providence County; Rhode Island"}},"44007012402":{"scores":{"income":44,"rent":46,"homeValue":43,"studentPopulation":37},"raw":{"income":76299,"rent":1377,"homeValue":309800,"studentPopulation":613,"population":2754,"name":"Census Tract 124.02; Providence County; Rhode Island"}},"44007012500":{"scores":{"income":37,"rent":31,"homeValue":47,"studentPopulation":51},"raw":{"income":65759,"rent":974,"homeValue":355000,"studentPopulation":971,"population":5131,"name":"Census Tract 125; Providence County; Rhode Island"}},"44007012601":{"scores":{"income":68,"rent":50,"homeValue":52,"studentPopulation":100},"raw":{"income":115731,"rent":1477,"homeValue":423500,"studentPopulation":3246,"population":4938,"name":"Census Tract 126.01; Providence County; Rhode Island"}},"44007012602":{"scores":{"income":58,"rent":30,"homeValue":54,"studentPopulation":72},"raw":{"income":100186,"rent":954,"homeValue":450100,"studentPopulation":1520,"population":7491,"name":"Census Tract 126.02; Providence County; Rhode Island"}},"44007012701":{"scores":{"income":65,"rent":62,"homeValue":55,"studentPopulation":57},"raw":{"income":110735,"rent":1800,"homeValue":463300,"studentPopulation":1138,"population":5177,"name":"Census Tract 127.01; Providence County; Rhode Island"}},"44007012702":{"scores":{"income":56,"rent":null,"homeValue":53,"studentPopulation":58},"raw":{"income":96150,"rent":null,"homeValue":437900,"studentPopulation":1162,"population":4627,"name":"Census Tract 127.02; Providence County; Rhode Island"}},"44007012801":{"scores":{"income":65,"rent":31,"homeValue":56,"studentPopulation":52},"raw":{"income":111092,"rent":990,"homeValue":472300,"studentPopulation":1001,"population":4762,"name":"Census Tract 128.01; Providence County; Rhode Island"}},"44007012802":{"scores":{"income":63,"rent":null,"homeValue":49,"studentPopulation":32},"raw":{"income":107974,"rent":null,"homeValue":383700,"studentPopulation":481,"population":2648,"name":"Census Tract 128.02; Providence County; Rhode Island"}},"44007012803":{"scores":{"income":60,"rent":46,"homeValue":56,"studentPopulation":60},"raw":{"income":102159,"rent":1364,"homeValue":468300,"studentPopulation":1199,"population":5298,"name":"Census Tract 128.03; Providence County; Rhode Island"}},"44007012900":{"scores":{"income":51,"rent":41,"homeValue":47,"studentPopulation":53},"raw":{"income":87448,"rent":1242,"homeValue":365200,"studentPopulation":1032,"population":4996,"name":"Census Tract 129; Providence County; Rhode Island"}},"44007013001":{"scores":{"income":87,"rent":38,"homeValue":50,"studentPopulation":53},"raw":{"income":146510,"rent":1176,"homeValue":396600,"studentPopulation":1021,"population":4015,"name":"Census Tract 130.01; Providence County; Rhode Island"}},"44007013002":{"scores":{"income":74,"rent":39,"homeValue":49,"studentPopulation":69},"raw":{"income":126484,"rent":1192,"homeValue":389500,"studentPopulation":1429,"population":7416,"name":"Census Tract 130.02; Providence County; Rhode Island"}},"44007013101":{"scores":{"income":67,"rent":null,"homeValue":52,"studentPopulation":55},"raw":{"income":113633,"rent":null,"homeValue":427800,"studentPopulation":1074,"population":5201,"name":"Census Tract 131.01; Providence County; Rhode Island"}},"44007013102":{"scores":{"income":65,"rent":49,"homeValue":47,"studentPopulation":49},"raw":{"income":111324,"rent":1443,"homeValue":356100,"studentPopulation":935,"population":5020,"name":"Census Tract 131.02; Providence County; Rhode Island"}},"44007013201":{"scores":{"income":77,"rent":57,"homeValue":54,"studentPopulation":36},"raw":{"income":131215,"rent":1660,"homeValue":443000,"studentPopulation":598,"population":4699,"name":"Census Tract 132.01; Providence County; Rhode Island"}},"44007013202":{"scores":{"income":55,"rent":42,"homeValue":54,"studentPopulation":58},"raw":{"income":94844,"rent":1279,"homeValue":453300,"studentPopulation":1157,"population":5818,"name":"Census Tract 132.02; Providence County; Rhode Island"}},"44007013300":{"scores":{"income":67,"rent":51,"homeValue":52,"studentPopulation":51},"raw":{"income":113646,"rent":1509,"homeValue":425300,"studentPopulation":968,"population":4523,"name":"Census Tract 133; Providence County; Rhode Island"}},"44007013400":{"scores":{"income":62,"rent":43,"homeValue":56,"studentPopulation":44},"raw":{"income":106940,"rent":1298,"homeValue":472900,"studentPopulation":795,"population":3700,"name":"Census Tract 134; Providence County; Rhode Island"}},"44007013500":{"scores":{"income":42,"rent":48,"homeValue":46,"studentPopulation":68},"raw":{"income":73138,"rent":1432,"homeValue":348600,"studentPopulation":1419,"population":5119,"name":"Census Tract 135; Providence County; Rhode Island"}},"44007013600":{"scores":{"income":52,"rent":51,"homeValue":43,"studentPopulation":39},"raw":{"income":89500,"rent":1507,"homeValue":303600,"studentPopulation":668,"population":3207,"name":"Census Tract 136; Providence County; Rhode Island"}},"44007013701":{"scores":{"income":50,"rent":40,"homeValue":45,"studentPopulation":54},"raw":{"income":87143,"rent":1216,"homeValue":334900,"studentPopulation":1049,"population":4582,"name":"Census Tract 137.01; Providence County; Rhode Island"}},"44007013702":{"scores":{"income":56,"rent":46,"homeValue":45,"studentPopulation":37},"raw":{"income":95608,"rent":1367,"homeValue":339900,"studentPopulation":625,"population":3217,"name":"Census Tract 137.02; Providence County; Rhode Island"}},"44007013800":{"scores":{"income":54,"rent":55,"homeValue":45,"studentPopulation":55},"raw":{"income":92927,"rent":1610,"homeValue":340900,"studentPopulation":1084,"population":5252,"name":"Census Tract 138; Providence County; Rhode Island"}},"44007013900":{"scores":{"income":45,"rent":49,"homeValue":50,"studentPopulation":43},"raw":{"income":77604,"rent":1451,"homeValue":404700,"studentPopulation":756,"population":3162,"name":"Census Tract 139; Providence County; Rhode Island"}},"44007014000":{"scores":{"income":48,"rent":55,"homeValue":46,"studentPopulation":75},"raw":{"income":82550,"rent":1619,"homeValue":346700,"studentPopulation":1594,"population":6866,"name":"Census Tract 140; Providence County; Rhode Island"}},"44007014100":{"scores":{"income":27,"rent":19,"homeValue":45,"studentPopulation":50},"raw":{"income":48889,"rent":675,"homeValue":332000,"studentPopulation":951,"population":4174,"name":"Census Tract 141; Providence County; Rhode Island"}},"44007014200":{"scores":{"income":55,"rent":45,"homeValue":45,"studentPopulation":43},"raw":{"income":93882,"rent":1344,"homeValue":337300,"studentPopulation":774,"population":4593,"name":"Census Tract 142; Providence County; Rhode Island"}},"44007014300":{"scores":{"income":64,"rent":52,"homeValue":53,"studentPopulation":53},"raw":{"income":109250,"rent":1524,"homeValue":435500,"studentPopulation":1033,"population":4709,"name":"Census Tract 143; Providence County; Rhode Island"}},"44007014400":{"scores":{"income":70,"rent":63,"homeValue":50,"studentPopulation":36},"raw":{"income":118885,"rent":1802,"homeValue":393800,"studentPopulation":593,"population":4086,"name":"Census Tract 144; Providence County; Rhode Island"}},"44007014501":{"scores":{"income":100,"rent":null,"homeValue":62,"studentPopulation":48},"raw":{"income":179268,"rent":null,"homeValue":548200,"studentPopulation":902,"population":4529,"name":"Census Tract 145.01; Providence County; Rhode Island"}},"44007014502":{"scores":{"income":47,"rent":46,"homeValue":46,"studentPopulation":48},"raw":{"income":80724,"rent":1386,"homeValue":346900,"studentPopulation":888,"population":4672,"name":"Census Tract 145.02; Providence County; Rhode Island"}},"44007014600":{"scores":{"income":84,"rent":47,"homeValue":59,"studentPopulation":80},"raw":{"income":142226,"rent":1405,"homeValue":511700,"studentPopulation":1722,"population":7236,"name":"Census Tract 146; Providence County; Rhode Island"}},"44007014700":{"scores":{"income":32,"rent":34,"homeValue":44,"studentPopulation":94},"raw":{"income":56005,"rent":1052,"homeValue":317900,"studentPopulation":2098,"population":8420,"name":"Census Tract 147; Providence County; Rhode Island"}},"44007014800":{"scores":{"income":60,"rent":67,"homeValue":50,"studentPopulation":48},"raw":{"income":103489,"rent":1923,"homeValue":396800,"studentPopulation":901,"population":5726,"name":"Census Tract 148; Providence County; Rhode Island"}},"44007015000":{"scores":{"income":60,"rent":38,"homeValue":43,"studentPopulation":70},"raw":{"income":102590,"rent":1170,"homeValue":310500,"studentPopulation":1464,"population":4717,"name":"Census Tract 150; Providence County; Rhode Island"}},"44007015100":{"scores":{"income":26,"rent":42,"homeValue":37,"studentPopulation":47},"raw":{"income":47529,"rent":1259,"homeValue":237500,"studentPopulation":882,"population":3998,"name":"Census Tract 151; Providence County; Rhode Island"}},"44007015200":{"scores":{"income":8,"rent":8,"homeValue":46,"studentPopulation":31},"raw":{"income":16543,"rent":393,"homeValue":349200,"studentPopulation":466,"population":2945,"name":"Census Tract 152; Providence County; Rhode Island"}},"44007015300":{"scores":{"income":34,"rent":40,"homeValue":40,"studentPopulation":62},"raw":{"income":59967,"rent":1225,"homeValue":275400,"studentPopulation":1258,"population":2823,"name":"Census Tract 153; Providence County; Rhode Island"}},"44007015400":{"scores":{"income":36,"rent":39,"homeValue":44,"studentPopulation":42},"raw":{"income":62566,"rent":1189,"homeValue":318500,"studentPopulation":745,"population":2405,"name":"Census Tract 154; Providence County; Rhode Island"}},"44007015500":{"scores":{"income":46,"rent":40,"homeValue":43,"studentPopulation":58},"raw":{"income":80458,"rent":1212,"homeValue":306300,"studentPopulation":1151,"population":4970,"name":"Census Tract 155; Providence County; Rhode Island"}},"44007015600":{"scores":{"income":54,"rent":39,"homeValue":51,"studentPopulation":37},"raw":{"income":93594,"rent":1187,"homeValue":405400,"studentPopulation":600,"population":3015,"name":"Census Tract 156; Providence County; Rhode Island"}},"44007015700":{"scores":{"income":59,"rent":45,"homeValue":43,"studentPopulation":43},"raw":{"income":101818,"rent":1353,"homeValue":306100,"studentPopulation":776,"population":3751,"name":"Census Tract 157; Providence County; Rhode Island"}},"44007015800":{"scores":{"income":57,"rent":38,"homeValue":45,"studentPopulation":49},"raw":{"income":97292,"rent":1167,"homeValue":336900,"studentPopulation":918,"population":3895,"name":"Census Tract 158; Providence County; Rhode Island"}},"44007015900":{"scores":{"income":39,"rent":44,"homeValue":38,"studentPopulation":37},"raw":{"income":67902,"rent":1324,"homeValue":240700,"studentPopulation":603,"population":3133,"name":"Census Tract 159; Providence County; Rhode Island"}},"44007016000":{"scores":{"income":46,"rent":43,"homeValue":49,"studentPopulation":58},"raw":{"income":79231,"rent":1298,"homeValue":380200,"studentPopulation":1160,"population":4068,"name":"Census Tract 160; Providence County; Rhode Island"}},"44007016100":{"scores":{"income":36,"rent":39,"homeValue":47,"studentPopulation":45},"raw":{"income":62775,"rent":1193,"homeValue":355500,"studentPopulation":819,"population":4304,"name":"Census Tract 161; Providence County; Rhode Island"}},"44007016300":{"scores":{"income":41,"rent":47,"homeValue":44,"studentPopulation":36},"raw":{"income":72022,"rent":1404,"homeValue":319000,"studentPopulation":599,"population":2896,"name":"Census Tract 163; Providence County; Rhode Island"}},"44007016400":{"scores":{"income":25,"rent":44,"homeValue":47,"studentPopulation":70},"raw":{"income":44760,"rent":1320,"homeValue":358000,"studentPopulation":1467,"population":5260,"name":"Census Tract 164; Providence County; Rhode Island"}},"44007016500":{"scores":{"income":53,"rent":46,"homeValue":58,"studentPopulation":44},"raw":{"income":91219,"rent":1374,"homeValue":494000,"studentPopulation":806,"population":3830,"name":"Census Tract 165; Providence County; Rhode Island"}},"44007016600":{"scores":{"income":56,"rent":39,"homeValue":46,"studentPopulation":31},"raw":{"income":96070,"rent":1180,"homeValue":353900,"studentPopulation":452,"population":1971,"name":"Census Tract 166; Providence County; Rhode Island"}},"44007016700":{"scores":{"income":27,"rent":38,"homeValue":44,"studentPopulation":40},"raw":{"income":49104,"rent":1174,"homeValue":320500,"studentPopulation":701,"population":3403,"name":"Census Tract 167; Providence County; Rhode Island"}},"44007016800":{"scores":{"income":53,"rent":44,"homeValue":42,"studentPopulation":42},"raw":{"income":91410,"rent":1320,"homeValue":297500,"studentPopulation":744,"population":3173,"name":"Census Tract 168; Providence County; Rhode Island"}},"44007016900":{"scores":{"income":59,"rent":36,"homeValue":47,"studentPopulation":25},"raw":{"income":101591,"rent":1119,"homeValue":358800,"studentPopulation":309,"population":1866,"name":"Census Tract 169; Providence County; Rhode Island"}},"44007017000":{"scores":{"income":34,"rent":47,"homeValue":42,"studentPopulation":45},"raw":{"income":59492,"rent":1389,"homeValue":292700,"studentPopulation":821,"population":4272,"name":"Census Tract 170; Providence County; Rhode Island"}},"44007017100":{"scores":{"income":37,"rent":45,"homeValue":42,"studentPopulation":57},"raw":{"income":65000,"rent":1339,"homeValue":298900,"studentPopulation":1125,"population":5198,"name":"Census Tract 171; Providence County; Rhode Island"}},"44007017300":{"scores":{"income":51,"rent":54,"homeValue":46,"studentPopulation":46},"raw":{"income":87400,"rent":1578,"homeValue":347200,"studentPopulation":851,"population":3843,"name":"Census Tract 173; Providence County; Rhode Island"}},"44007017400":{"scores":{"income":31,"rent":33,"homeValue":46,"studentPopulation":61},"raw":{"income":54412,"rent":1028,"homeValue":341500,"studentPopulation":1243,"population":4217,"name":"Census Tract 174; Providence County; Rhode Island"}},"44007017500":{"scores":{"income":42,"rent":49,"homeValue":41,"studentPopulation":44},"raw":{"income":73234,"rent":1447,"homeValue":288500,"studentPopulation":801,"population":3419,"name":"Census Tract 175; Providence County; Rhode Island"}},"44007017600":{"scores":{"income":27,"rent":39,"homeValue":41,"studentPopulation":41},"raw":{"income":47951,"rent":1190,"homeValue":278800,"studentPopulation":710,"population":2851,"name":"Census Tract 176; Providence County; Rhode Island"}},"44007017700":{"scores":{"income":52,"rent":38,"homeValue":44,"studentPopulation":37},"raw":{"income":89063,"rent":1165,"homeValue":328400,"studentPopulation":614,"population":3520,"name":"Census Tract 177; Providence County; Rhode Island"}},"44007017800":{"scores":{"income":23,"rent":34,"homeValue":44,"studentPopulation":27},"raw":{"income":42432,"rent":1060,"homeValue":328500,"studentPopulation":344,"population":2939,"name":"Census Tract 178; Providence County; Rhode Island"}},"44007017900":{"scores":{"income":18,"rent":31,"homeValue":40,"studentPopulation":40},"raw":{"income":33895,"rent":993,"homeValue":273700,"studentPopulation":695,"population":2985,"name":"Census Tract 179; Providence County; Rhode Island"}},"44007018000":{"scores":{"income":13,"rent":21,"homeValue":37,"studentPopulation":29},"raw":{"income":25933,"rent":717,"homeValue":229000,"studentPopulation":404,"population":2585,"name":"Census Tract 180; Providence County; Rhode Island"}},"44007018100":{"scores":{"income":31,"rent":41,"homeValue":35,"studentPopulation":37},"raw":{"income":54776,"rent":1248,"homeValue":208800,"studentPopulation":623,"population":3178,"name":"Census Tract 181; Providence County; Rhode Island"}},"44007018200":{"scores":{"income":53,"rent":51,"homeValue":37,"studentPopulation":38},"raw":{"income":91591,"rent":1512,"homeValue":234700,"studentPopulation":638,"population":3162,"name":"Census Tract 182; Providence County; Rhode Island"}},"44007018300":{"scores":{"income":27,"rent":40,"homeValue":45,"studentPopulation":34},"raw":{"income":48668,"rent":1226,"homeValue":337000,"studentPopulation":530,"population":1505,"name":"Census Tract 183; Providence County; Rhode Island"}},"44007018400":{"scores":{"income":37,"rent":null,"homeValue":44,"studentPopulation":61},"raw":{"income":64679,"rent":null,"homeValue":322100,"studentPopulation":1238,"population":6541,"name":"Census Tract 184; Providence County; Rhode Island"}},"44007018500":{"scores":{"income":49,"rent":41,"homeValue":44,"studentPopulation":35},"raw":{"income":85428,"rent":1244,"homeValue":322100,"studentPopulation":560,"population":2776,"name":"Census Tract 185; Providence County; Rhode Island"}},"44009041500":{"scores":{"income":48,"rent":null,"homeValue":100,"studentPopulation":15},"raw":{"income":83190,"rent":null,"homeValue":1301100,"studentPopulation":45,"population":777,"name":"Census Tract 415; Washington County; Rhode Island"}},"44009050102":{"scores":{"income":92,"rent":77,"homeValue":69,"studentPopulation":38},"raw":{"income":156172,"rent":2185,"homeValue":643000,"studentPopulation":626,"population":2523,"name":"Census Tract 501.02; Washington County; Rhode Island"}},"44009050103":{"scores":{"income":53,"rent":42,"homeValue":47,"studentPopulation":60},"raw":{"income":91500,"rent":1260,"homeValue":359900,"studentPopulation":1209,"population":5224,"name":"Census Tract 501.03; Washington County; Rhode Island"}},"44009050104":{"scores":{"income":86,"rent":85,"homeValue":58,"studentPopulation":47},"raw":{"income":144963,"rent":2393,"homeValue":499000,"studentPopulation":879,"population":3798,"name":"Census Tract 501.04; Washington County; Rhode Island"}},"44009050301":{"scores":{"income":68,"rent":40,"homeValue":65,"studentPopulation":51},"raw":{"income":115313,"rent":1208,"homeValue":589900,"studentPopulation":977,"population":5333,"name":"Census Tract 503.01; Washington County; Rhode Island"}},"44009050302":{"scores":{"income":67,"rent":21,"homeValue":64,"studentPopulation":32},"raw":{"income":114196,"rent":728,"homeValue":581500,"studentPopulation":473,"population":2936,"name":"Census Tract 503.02; Washington County; Rhode Island"}},"44009050401":{"scores":{"income":94,"rent":38,"homeValue":66,"studentPopulation":69},"raw":{"income":158036,"rent":1161,"homeValue":599500,"studentPopulation":1433,"population":5276,"name":"Census Tract 504.01; Washington County; Rhode Island"}},"44009050402":{"scores":{"income":78,"rent":59,"homeValue":69,"studentPopulation":36},"raw":{"income":131875,"rent":1704,"homeValue":641900,"studentPopulation":586,"population":2769,"name":"Census Tract 504.02; Washington County; Rhode Island"}},"44009050500":{"scores":{"income":65,"rent":44,"homeValue":59,"studentPopulation":82},"raw":{"income":111250,"rent":1317,"homeValue":509200,"studentPopulation":1767,"population":7195,"name":"Census Tract 505; Washington County; Rhode Island"}},"44009050600":{"scores":{"income":73,"rent":54,"homeValue":53,"studentPopulation":97},"raw":{"income":124653,"rent":1580,"homeValue":435800,"studentPopulation":2177,"population":8142,"name":"Census Tract 506; Washington County; Rhode Island"}},"44009050701":{"scores":{"income":54,"rent":13,"homeValue":53,"studentPopulation":43},"raw":{"income":92273,"rent":531,"homeValue":438000,"studentPopulation":775,"population":4009,"name":"Census Tract 507.01; Washington County; Rhode Island"}},"44009050702":{"scores":{"income":59,"rent":55,"homeValue":47,"studentPopulation":52},"raw":{"income":100486,"rent":1599,"homeValue":358600,"studentPopulation":997,"population":4411,"name":"Census Tract 507.02; Washington County; Rhode Island"}},"44009050801":{"scores":{"income":37,"rent":44,"homeValue":49,"studentPopulation":54},"raw":{"income":64396,"rent":1326,"homeValue":386400,"studentPopulation":1059,"population":5655,"name":"Census Tract 508.01; Washington County; Rhode Island"}},"44009050802":{"scores":{"income":52,"rent":54,"homeValue":54,"studentPopulation":29},"raw":{"income":90332,"rent":1588,"homeValue":451400,"studentPopulation":417,"population":3681,"name":"Census Tract 508.02; Washington County; Rhode Island"}},"44009050901":{"scores":{"income":59,"rent":36,"homeValue":53,"studentPopulation":64},"raw":{"income":101621,"rent":1115,"homeValue":442400,"studentPopulation":1315,"population":7020,"name":"Census Tract 509.01; Washington County; Rhode Island"}},"44009050902":{"scores":{"income":71,"rent":39,"homeValue":59,"studentPopulation":46},"raw":{"income":121377,"rent":1190,"homeValue":515100,"studentPopulation":852,"population":5128,"name":"Census Tract 509.02; Washington County; Rhode Island"}},"44009051000":{"scores":{"income":84,"rent":47,"homeValue":100,"studentPopulation":21},"raw":{"income":143088,"rent":1395,"homeValue":1103800,"studentPopulation":193,"population":1849,"name":"Census Tract 510; Washington County; Rhode Island"}},"44009051101":{"scores":{"income":69,"rent":55,"homeValue":61,"studentPopulation":44},"raw":{"income":117372,"rent":1602,"homeValue":540400,"studentPopulation":797,"population":4897,"name":"Census Tract 511.01; Washington County; Rhode Island"}},"44009051102":{"scores":{"income":60,"rent":42,"homeValue":58,"studentPopulation":32},"raw":{"income":102250,"rent":1274,"homeValue":501600,"studentPopulation":485,"population":3154,"name":"Census Tract 511.02; Washington County; Rhode Island"}},"44009051201":{"scores":{"income":74,"rent":40,"homeValue":57,"studentPopulation":64},"raw":{"income":126028,"rent":1213,"homeValue":483500,"studentPopulation":1303,"population":5121,"name":"Census Tract 512.01; Washington County; Rhode Island"}},"44009051202":{"scores":{"income":41,"rent":45,"homeValue":58,"studentPopulation":44},"raw":{"income":72143,"rent":1338,"homeValue":502200,"studentPopulation":790,"population":4324,"name":"Census Tract 512.02; Washington County; Rhode Island"}},"44009051302":{"scores":{"income":70,"rent":null,"homeValue":73,"studentPopulation":36},"raw":{"income":119279,"rent":null,"homeValue":690900,"studentPopulation":577,"population":4099,"name":"Census Tract 513.02; Washington County; Rhode Island"}},"44009051304":{"scores":{"income":57,"rent":null,"homeValue":67,"studentPopulation":25},"raw":{"income":98611,"rent":null,"homeValue":612100,"studentPopulation":304,"population":2134,"name":"Census Tract 513.04; Washington County; Rhode Island"}},"44009051305":{"scores":{"income":62,"rent":39,"homeValue":59,"studentPopulation":57},"raw":{"income":105459,"rent":1186,"homeValue":511200,"studentPopulation":1124,"population":4427,"name":"Census Tract 513.05; Washington County; Rhode Island"}},"44009051306":{"scores":{"income":72,"rent":62,"homeValue":64,"studentPopulation":76},"raw":{"income":122155,"rent":1790,"homeValue":574400,"studentPopulation":1618,"population":6206,"name":"Census Tract 513.06; Washington County; Rhode Island"}},"44009051400":{"scores":{"income":70,"rent":22,"homeValue":67,"studentPopulation":100},"raw":{"income":119444,"rent":750,"homeValue":618500,"studentPopulation":5529,"population":5762,"name":"Census Tract 514; Washington County; Rhode Island"}},"44009051502":{"scores":{"income":61,"rent":67,"homeValue":68,"studentPopulation":90},"raw":{"income":104174,"rent":1920,"homeValue":627000,"studentPopulation":1984,"population":6471,"name":"Census Tract 515.02; Washington County; Rhode Island"}},"44009051503":{"scores":{"income":47,"rent":52,"homeValue":87,"studentPopulation":42},"raw":{"income":81461,"rent":1519,"homeValue":867000,"studentPopulation":734,"population":3413,"name":"Census Tract 515.03; Washington County; Rhode Island"}},"44009051504":{"scores":{"income":43,"rent":60,"homeValue":85,"studentPopulation":82},"raw":{"income":74963,"rent":1746,"homeValue":836300,"studentPopulation":1785,"population":4610,"name":"Census Tract 515.04; Washington County; Rhode Island"}},"44009990100":{"scores":{"income":null,"rent":null,"homeValue":null,"studentPopulation":13},"raw":{"income":null,"rent":null,"homeValue":null,"studentPopulation":0,"population":null,"name":"Census Tract 9901; Washington County; Rhode Island"}},"44009990200":{"scores":{"income":null,"rent":null,"homeValue":null,"studentPopulation":13},"raw":{"income":null,"rent":null,"homeValue":null,"studentPopulation":0,"population":null,"name":"Census Tract 9902; Washington County; Rhode Island"}}}
